ducks/__init__.py
ducks/api.md
ducks/btree.py
ducks/concurrent/__init__.py
ducks/concurrent/main.py
ducks/constants.py
ducks/exceptions.py
ducks/frozen/__init__.py
ducks/frozen/frozen_attr.py
ducks/frozen/init_helpers.py
ducks/frozen/main.py
ducks/frozen/utils.py
ducks/mutable/__init__.py
ducks/mutable/main.py
ducks/mutable/mutable_attr.py
ducks/pickling.py
ducks/utils.py
ducks-0.5.1.dist-info/LICENSE
ducks-0.5.1.dist-info/WHEEL
ducks-0.5.1.dist-info/METADATA
ducks-0.5.1.dist-info/RECORD
